kosher/__init__.py
kosher/gcm.py
kosher/mixin.py
kosher-0.1.6.dist-info/LICENSE
kosher-0.1.6.dist-info/METADATA
kosher-0.1.6.dist-info/WHEEL
kosher-0.1.6.dist-info/top_level.txt
kosher-0.1.6.dist-info/RECORD
